g16_input_generator/__init__.py
g16_input_generator/__main__.py
g16_input_generator/main.py
g16_input_generator-0.3.3.dist-info/METADATA
g16_input_generator-0.3.3.dist-info/WHEEL
g16_input_generator-0.3.3.dist-info/entry_points.txt
g16_input_generator-0.3.3.dist-info/top_level.txt
g16_input_generator-0.3.3.dist-info/RECORD
