Metadata-Version: 2.1
Name: g16-input-generator
Version: 0.3.3
Requires-Dist: rdkit
